hehd/__init__.py
hehd/nodes.py
hehd/tags.py
hehd/test.py
hehd/rsc/__init__.py
hehd/rsc/doc.py
hehd/rsc/document/__init__.py
hehd/rsc/document/create.py
hehd/rsc/document/nodes.py
hehd/rsc/document/tags.py
hehd/rsc/nodes/__init__.py
hehd/rsc/nodes/code.py
hehd/rsc/nodes/comment.py
hehd/rsc/nodes/content.py
hehd/rsc/nodes/group.py
hehd/rsc/nodes/node.py
hehd/rsc/nodes/tag.py
hehd/rsc/tags/__init__.py
hehd/rsc/tags/a.py
hehd/rsc/tags/body.py
hehd/rsc/tags/div.py
hehd/rsc/tags/head.py
hehd/rsc/tags/html.py
hehd/rsc/tags/input_text.py
hehd/rsc/tags/link.py
hehd/rsc/tags/span.py
hehd/rsc/tags/title.py
hehd-1.0.1.dist-info/LICENSE.rst
hehd-1.0.1.dist-info/METADATA
hehd-1.0.1.dist-info/WHEEL
hehd-1.0.1.dist-info/top_level.txt
hehd-1.0.1.dist-info/RECORD
