Metadata-Version: 2.1
Name: hehd
Version: 1.0.1
Summary: Python Html Document Generator
Home-page: https://py.hebill.net/hehd
Author: He Bill
Author-email: hebill@me.com
Requires-Python: >=3.12
License-File: LICENSE.rst
